BIM360/__init__.py
CLASSES/__init__.py
DATAMANAGEMENT/__init__.py
Utils/__init__.py
FMOARPG-0.0.7.dist-info/LICENCE.txt
FMOARPG-0.0.7.dist-info/METADATA
FMOARPG-0.0.7.dist-info/WHEEL
FMOARPG-0.0.7.dist-info/top_level.txt
FMOARPG-0.0.7.dist-info/RECORD
